rustyaml/__init__.py
rustyaml/_rustyaml.cp37-win_amd64.pyd
rustyaml-0.1.1.dist-info/METADATA
rustyaml-0.1.1.dist-info/WHEEL
rustyaml-0.1.1.dist-info/top_level.txt
rustyaml-0.1.1.dist-info/RECORD
