Metadata-Version: 2.1
Name: rustyaml
Version: 0.1.1
Summary: Python bindings for rust-yaml
Home-page: UNKNOWN
Author: Will Eaton
Author-email: me@wseaton.com
License: UNKNOWN
Platform: UNKNOWN
Requires-Python: >=3.6.0,<4.0
